[
{"Time": "00:00", "Quote_Time": "Happy Valentine's Day Jessie", "Quote": "Happy Valentine's Day Jessie", "Title": "MESS", "Author": "Mathew Hobers"},
{"Time": "00:00", "Quote_Time": "sweet dreams", "Quote": "Hope you're enjoying your night - and sweet dreams if you're sleeping <3", "Title": "Miss u", "Author": "Mountain Goat"},
{"Time": "00:00", "Quote_Time": "Jessie", "Quote": "Hope you're enjoying your night reading or whatever you're up to Jessie :)     Ahhh DnD level up. Enjoy!", "Title": "Jessie's \"Friday\" Night", "Author": "Mystery Man ;)"}
]
